illoominate-0.9.3.dist-info/METADATA
illoominate-0.9.3.dist-info/WHEEL
illoominate/__init__.py
illoominate/illoominate.cp310-win_amd64.pyd
illoominate-0.9.3.dist-info/RECORD
