Metadata-Version: 2.3
Name: illoominate
Version: 0.9.3
Classifier: Programming Language :: Rust
Classifier: Programming Language :: Python :: Implementation :: CPython
Classifier: Programming Language :: Python :: Implementation :: PyPy
Summary: A scalable library designed to compute data importance scores for interaction data in sequential kNN-based recommender systems.
Author-email: Barrie Kersbergen <kersbergenb@gmail.com>
Maintainer-email: Barrie Kersbergen <kersbergenb@gmail.com>
Requires-Python: >=3.10
